lessqlite/UNKNOWN.egg-info/PKG-INFO
lessqlite/UNKNOWN.egg-info/SOURCES.txt
lessqlite/UNKNOWN.egg-info/dependency_links.txt
lessqlite/UNKNOWN.egg-info/top_level.txt
lessqlite/__init__.py
lessqlite/core.py
lessqlite-0.1.4.dist-info/entry_points.txt
lessqlite-0.1.4.dist-info/WHEEL
lessqlite-0.1.4.dist-info/METADATA
lessqlite-0.1.4.dist-info/RECORD
